[{"whichDotOnSpoke":"0","trope":"Data Pad","tags":"padd","trope_detail":"Pike reads Padd.","color":"goldshirt","ringAttr":"0","dotAttr":"0","ref_num":"100","ep_num":"1","ep_title":"The Cage","s":"1","e":"0"},{"whichDotOnSpoke":"0","trope":"Data Pad","tags":"padd spock","trope_detail":"Spock writes on Padd.","color":"spock","ringAttr":"1","dotAttr":"0","ref_num":"101","ep_num":"2","ep_title":"The Man Trap","s":"1","e":"1"},{"whichDotOnSpoke":"1","trope":"Data Pad","tags":"padd spock","trope_detail":"Sulu writes on padd while talking to Uhura on bridge.","color":"spock","ringAttr":"1","dotAttr":"0","ref_num":"101","ep_num":"2","ep_title":"The Man Trap","s":"1","e":"1"},{"whichDotOnSpoke":"0","trope":"Data Pad","tags":"padd kirk","trope_detail":"Kirk reads status report on Padd and hands to Uhura.","color":"kirk","ringAttr":"1","dotAttr":"0","ref_num":"102","ep_num":"3","ep_title":"Charlie X","s":"1","e":"2"},{"whichDotOnSpoke":"1","trope":"Data Pad","tags":"padd kirk","trope_detail":"Kirk signs Padd.","color":"kirk","ringAttr":"1","dotAttr":"0","ref_num":"102","ep_num":"3","ep_title":"Charlie X","s":"1","e":"2"},{"whichDotOnSpoke":"0","trope":"Data Pad","tags":"padd","trope_detail":"Crewman with Padd.","color":"gray","ringAttr":"0","dotAttr":"0","ref_num":"104","ep_num":"5","ep_title":"The Naked Time","s":"1","e":"4"},{"whichDotOnSpoke":"1","trope":"Data Pad","tags":"padd kirk","trope_detail":"Kirk signs Padd.","color":"kirk","ringAttr":"1","dotAttr":"0","ref_num":"104","ep_num":"5","ep_title":"The Naked Time","s":"1","e":"4"},{"whichDotOnSpoke":"2","trope":"Data Pad","tags":"padd kirk","trope_detail":"Kirk with Padd.","color":"kirk","ringAttr":"1","dotAttr":"0","ref_num":"104","ep_num":"5","ep_title":"The Naked Time","s":"1","e":"4"},{"whichDotOnSpoke":"3","trope":"Data Pad","tags":"padd kirk","trope_detail":"Kirk with Padd.","color":"kirk","ringAttr":"1","dotAttr":"0","ref_num":"104","ep_num":"5","ep_title":"The Naked Time","s":"1","e":"4"},{"whichDotOnSpoke":"4","trope":"Data Pad","tags":"padd","trope_detail":"Nurse Chapel with Padd.","color":"nurse_chapel","ringAttr":"0","dotAttr":"1","ref_num":"104","ep_num":"5","ep_title":"The Naked Time","s":"1","e":"4"},{"whichDotOnSpoke":"0","trope":"Data Pad","tags":"padd spock rand","trope_detail":"Spock writes on Padd and hands to Yeoman Rand.","color":"spock","ringAttr":"1","dotAttr":"0","ref_num":"105","ep_num":"6","ep_title":"The Enemy Within","s":"1","e":"5"},{"whichDotOnSpoke":"0","trope":"Data Pad","tags":"padd kirk","trope_detail":"Kirk with Padd on bridge.","color":"kirk","ringAttr":"1","dotAttr":"0","ref_num":"106","ep_num":"7","ep_title":"Mudd's Women","s":"1","e":"6"},{"whichDotOnSpoke":"1","trope":"Data Pad","tags":"padd kirk","trope_detail":"Kirk with Padd on bridge.","color":"kirk","ringAttr":"1","dotAttr":"0","ref_num":"106","ep_num":"7","ep_title":"Mudd's Women","s":"1","e":"6"},{"whichDotOnSpoke":"2","trope":"Data Pad","tags":"padd kirk","trope_detail":"Kirk with Padd on desk in briefing room during hearing.","color":"kirk","ringAttr":"1","dotAttr":"0","ref_num":"106","ep_num":"7","ep_title":"Mudd's Women","s":"1","e":"6"},{"whichDotOnSpoke":"3","trope":"Data Pad","tags":"padd kirk","trope_detail":"Padd on desk in Kirks quarters while Kirk is talking to Harry Mudd.","color":"kirk","ringAttr":"1","dotAttr":"0","ref_num":"106","ep_num":"7","ep_title":"Mudd's Women","s":"1","e":"6"},{"whichDotOnSpoke":"0","trope":"Data Pad","tags":"padd kirk","trope_detail":"Kirk signs Padd","color":"kirk","ringAttr":"1","dotAttr":"0","ref_num":"107","ep_num":"8","ep_title":"What Are Little Girls Made Of?","s":"1","e":"7"},{"whichDotOnSpoke":"1","trope":"Data Pad","tags":"padd spock","trope_detail":"Spock with Padd.","color":"spock","ringAttr":"1","dotAttr":"0","ref_num":"107","ep_num":"8","ep_title":"What Are Little Girls Made Of?","s":"1","e":"7"},{"whichDotOnSpoke":"0","trope":"Data Pad","tags":"padd","trope_detail":"McCoy with Padd in sick bay.","color":"mccoy","ringAttr":"0","dotAttr":"2","ref_num":"109","ep_num":"10","ep_title":"Dagger of the Mind","s":"1","e":"9"},{"whichDotOnSpoke":"1","trope":"Data Pad","tags":"padd","trope_detail":"Transport tech with Padd.","color":"whitesmoke","ringAttr":"0","dotAttr":"0","ref_num":"109","ep_num":"10","ep_title":"Dagger of the Mind","s":"1","e":"9"},{"whichDotOnSpoke":"0","trope":"Data Pad","tags":"padd","trope_detail":"Lt. Bailey with Padd on briefing room table.","color":"goldshirt","ringAttr":"0","dotAttr":"0","ref_num":"110","ep_num":"11","ep_title":"The Corbomite Maneuver","s":"1","e":"10"},{"whichDotOnSpoke":"1","trope":"Data Pad","tags":"padd","trope_detail":"Lt. Bailey writes on Padd.","color":"goldshirt","ringAttr":"0","dotAttr":"0","ref_num":"110","ep_num":"11","ep_title":"The Corbomite Maneuver","s":"1","e":"10"},{"whichDotOnSpoke":"2","trope":"Data Pad","tags":"padd","trope_detail":"Redshirt with Padd on bridge.","color":"redshirt","ringAttr":"0","dotAttr":"0","ref_num":"110","ep_num":"11","ep_title":"The Corbomite Maneuver","s":"1","e":"10"},{"whichDotOnSpoke":"3","trope":"Data Pad","tags":"padd scotty","trope_detail":"Scotty writes on Padd.","color":"scotty","ringAttr":"0","dotAttr":"2","ref_num":"110","ep_num":"11","ep_title":"The Corbomite Maneuver","s":"1","e":"10"},{"whichDotOnSpoke":"4","trope":"Data Pad","tags":"padd spock","trope_detail":"Spock writes on Padd.","color":"spock","ringAttr":"1","dotAttr":"0","ref_num":"110","ep_num":"11","ep_title":"The Corbomite Maneuver","s":"1","e":"10"},{"whichDotOnSpoke":"5","trope":"Data Pad","tags":"padd","trope_detail":"Padd on briefing room table.","color":"whitesmoke","ringAttr":"0","dotAttr":"0","ref_num":"110","ep_num":"11","ep_title":"The Corbomite Maneuver","s":"1","e":"10"},{"whichDotOnSpoke":"0","trope":"Data Pad","tags":"padd","trope_detail":"Crewman with Padd on briefing room table.","color":"gray","ringAttr":"0","dotAttr":"0","ref_num":"111","ep_num":"12","ep_title":"The Menagerie, Part I","s":"1","e":"11"},{"whichDotOnSpoke":"1","trope":"Data Pad","tags":"padd kirk","trope_detail":"Kirk signs Padd","color":"kirk","ringAttr":"1","dotAttr":"0","ref_num":"111","ep_num":"12","ep_title":"The Menagerie, Part I","s":"1","e":"11"},{"whichDotOnSpoke":"2","trope":"Data Pad","tags":"padd","trope_detail":"Commodore Mendez has Padd on table in briefing room.","color":"redshirt","ringAttr":"0","dotAttr":"0","ref_num":"111","ep_num":"12","ep_title":"The Menagerie, Part I","s":"1","e":"11"},{"whichDotOnSpoke":"3","trope":"Data Pad","tags":"padd","trope_detail":"Commodore Mendez has Padd on table in briefing room.","color":"redshirt","ringAttr":"0","dotAttr":"0","ref_num":"111","ep_num":"12","ep_title":"The Menagerie, Part I","s":"1","e":"11"},{"whichDotOnSpoke":"4","trope":"Data Pad","tags":"padd","trope_detail":"Red-Skirt lay Padd on table by Spock in briefing room.","color":"red-Skirt","ringAttr":"0","dotAttr":"0","ref_num":"111","ep_num":"12","ep_title":"The Menagerie, Part I","s":"1","e":"11"},{"whichDotOnSpoke":"5","trope":"Data Pad","tags":"padd spock","trope_detail":"Spock with Padd on briefing table.","color":"spock","ringAttr":"1","dotAttr":"0","ref_num":"111","ep_num":"12","ep_title":"The Menagerie, Part I","s":"1","e":"11"},{"whichDotOnSpoke":"6","trope":"Data Pad","tags":"padd uhura","trope_detail":"Padd on Uhura's bridge station.","color":"uhura","ringAttr":"1","dotAttr":"0","ref_num":"111","ep_num":"12","ep_title":"The Menagerie, Part I","s":"1","e":"11"},{"whichDotOnSpoke":"7","trope":"Data Pad","tags":"padd uhura","trope_detail":"Uhura with Padd on briefing room table.","color":"uhura","ringAttr":"1","dotAttr":"0","ref_num":"111","ep_num":"12","ep_title":"The Menagerie, Part I","s":"1","e":"11"},{"whichDotOnSpoke":"8","trope":"Data Pad","tags":"padd","trope_detail":"Padd on desk of computer center at command base.","color":"whitesmoke","ringAttr":"0","dotAttr":"0","ref_num":"111","ep_num":"12","ep_title":"The Menagerie, Part I","s":"1","e":"11"},{"whichDotOnSpoke":"0","trope":"Data Pad","tags":"padd kirk","trope_detail":"Kirk reads report on Padd.","color":"kirk","ringAttr":"1","dotAttr":"0","ref_num":"113","ep_num":"14","ep_title":"The Conscience of the King","s":"1","e":"13"},{"whichDotOnSpoke":"1","trope":"Data Pad","tags":"padd kirk","trope_detail":"Kirk signs Padd","color":"kirk","ringAttr":"1","dotAttr":"0","ref_num":"113","ep_num":"14","ep_title":"The Conscience of the King","s":"1","e":"13"},{"whichDotOnSpoke":"2","trope":"Data Pad","tags":"padd","trope_detail":"McCoy with Padd in sick bay.","color":"mccoy","ringAttr":"0","dotAttr":"2","ref_num":"113","ep_num":"14","ep_title":"The Conscience of the King","s":"1","e":"13"},{"whichDotOnSpoke":"3","trope":"Data Pad","tags":"padd","trope_detail":"McCoy with Padd in sick bay.","color":"mccoy","ringAttr":"0","dotAttr":"2","ref_num":"113","ep_num":"14","ep_title":"The Conscience of the King","s":"1","e":"13"},{"whichDotOnSpoke":"4","trope":"Data Pad","tags":"padd uhura","trope_detail":"Uhura writes on Padd.","color":"uhura","ringAttr":"1","dotAttr":"0","ref_num":"113","ep_num":"14","ep_title":"The Conscience of the King","s":"1","e":"13"},{"whichDotOnSpoke":"0","trope":"Data Pad","tags":"padd spock","trope_detail":"Spock with Padd on bridge.","color":"spock","ringAttr":"1","dotAttr":"0","ref_num":"114","ep_num":"15","ep_title":"Balance of Terror","s":"1","e":"14"},{"whichDotOnSpoke":"0","trope":"Data Pad","tags":"padd small","trope_detail":"Yeoman Barrows with Padd (small).","color":"red-Skirt","ringAttr":"0","dotAttr":"0","ref_num":"115","ep_num":"16","ep_title":"Shore Leave","s":"1","e":"15"},{"whichDotOnSpoke":"1","trope":"Data Pad","tags":"padd spock","trope_detail":"Spock reads report from Padd to Kirk about a crew member needing R&R. Its about Kirk. Kirk then has to go on R&R.","color":"spock","ringAttr":"1","dotAttr":"0","ref_num":"115","ep_num":"16","ep_title":"Shore Leave","s":"1","e":"15"},{"whichDotOnSpoke":"0","trope":"Data Pad","tags":"padd small","trope_detail":"Crewman reads report from Padd (small).","color":"gray","ringAttr":"0","dotAttr":"0","ref_num":"116","ep_num":"17","ep_title":"The Galileo Seven","s":"1","e":"16"},{"whichDotOnSpoke":"0","trope":"Data Pad","tags":"padd kirk","trope_detail":"Kirk signs Padd","color":"kirk","ringAttr":"1","dotAttr":"0","ref_num":"117","ep_num":"18","ep_title":"The Squire of Gothos","s":"1","e":"17"},{"whichDotOnSpoke":"1","trope":"Data Pad","tags":"padd spock","trope_detail":"Spock writes on Padd.","color":"spock","ringAttr":"1","dotAttr":"0","ref_num":"117","ep_num":"18","ep_title":"The Squire of Gothos","s":"1","e":"17"},{"whichDotOnSpoke":"0","trope":"Data Pad","tags":"padd kirk","trope_detail":"Kirk with Padd on desk in briefing room.","color":"kirk","ringAttr":"1","dotAttr":"0","ref_num":"119","ep_num":"20","ep_title":"Tomorrow Is Yesterday","s":"1","e":"19"},{"whichDotOnSpoke":"1","trope":"Data Pad","tags":"padd","trope_detail":"Captain Christopher sketcHe's layout of air force base on Padd.","color":"whitesmoke","ringAttr":"0","dotAttr":"0","ref_num":"119","ep_num":"20","ep_title":"Tomorrow Is Yesterday","s":"1","e":"19"},{"whichDotOnSpoke":"0","trope":"Data Pad","tags":"padd kirk","trope_detail":"Padd on desk at Kirks court martial.","color":"kirk","ringAttr":"1","dotAttr":"0","ref_num":"120","ep_num":"21","ep_title":"Court Martial","s":"1","e":"20"},{"whichDotOnSpoke":"1","trope":"Data Pad","tags":"padd uhura","trope_detail":"Uhura at station with Padd.","color":"uhura","ringAttr":"1","dotAttr":"0","ref_num":"120","ep_num":"21","ep_title":"Court Martial","s":"1","e":"20"},{"whichDotOnSpoke":"0","trope":"Data Pad","tags":"padd","trope_detail":"Blueshirt with Padd sticks computer disk in slot.","color":"blueshirt","ringAttr":"0","dotAttr":"0","ref_num":"121","ep_num":"22","ep_title":"The Return of the Archons","s":"1","e":"21"},{"whichDotOnSpoke":"1","trope":"Data Pad","tags":"padd","trope_detail":"Goldshirt with Padd.","color":"goldshirt","ringAttr":"0","dotAttr":"0","ref_num":"121","ep_num":"22","ep_title":"The Return of the Archons","s":"1","e":"21"},{"whichDotOnSpoke":"0","trope":"Data Pad","tags":"padd kirk","trope_detail":"Kirk signs Padd and return to a Red-Skirt.","color":"kirk","ringAttr":"1","dotAttr":"0","ref_num":"122","ep_num":"23","ep_title":"Space Seed","s":"1","e":"22"},{"whichDotOnSpoke":"1","trope":"Data Pad","tags":"padd","trope_detail":"McCoy writes on pad.","color":"mccoy","ringAttr":"0","dotAttr":"2","ref_num":"122","ep_num":"23","ep_title":"Space Seed","s":"1","e":"22"},{"whichDotOnSpoke":"2","trope":"Data Pad","tags":"padd spock","trope_detail":"Spock reads Padd.","color":"spock","ringAttr":"1","dotAttr":"0","ref_num":"122","ep_num":"23","ep_title":"Space Seed","s":"1","e":"22"},{"whichDotOnSpoke":"3","trope":"Data Pad","tags":"padd uhura","trope_detail":"Uhura with Padd on bridge.","color":"uhura","ringAttr":"1","dotAttr":"0","ref_num":"122","ep_num":"23","ep_title":"Space Seed","s":"1","e":"22"},{"whichDotOnSpoke":"0","trope":"Data Pad","tags":"padd","trope_detail":"Yeoman Tamura reads Padd.","color":"blue-Skirt","ringAttr":"0","dotAttr":"0","ref_num":"123","ep_num":"24","ep_title":"A Taste of Armageddon","s":"1","e":"23"},{"whichDotOnSpoke":"0","trope":"Data Pad","tags":"padd","trope_detail":"McCoy read medical report on Sandoval from Padd.","color":"mccoy","ringAttr":"0","dotAttr":"2","ref_num":"124","ep_num":"25","ep_title":"This Side of Paradise","s":"1","e":"24"},{"whichDotOnSpoke":"1","trope":"Data Pad","tags":"padd","trope_detail":"McCoy with Padd during muster of settlers.","color":"mccoy","ringAttr":"0","dotAttr":"2","ref_num":"124","ep_num":"25","ep_title":"This Side of Paradise","s":"1","e":"24"},{"whichDotOnSpoke":"2","trope":"Data Pad","tags":"padd","trope_detail":"Redshirt with Padd on bridge.","color":"redshirt","ringAttr":"0","dotAttr":"0","ref_num":"124","ep_num":"25","ep_title":"This Side of Paradise","s":"1","e":"24"},{"whichDotOnSpoke":"3","trope":"Data Pad","tags":"padd spock","trope_detail":"Spock writes on Padd.","color":"spock","ringAttr":"1","dotAttr":"0","ref_num":"124","ep_num":"25","ep_title":"This Side of Paradise","s":"1","e":"24"},{"whichDotOnSpoke":"4","trope":"Data Pad","tags":"padd","trope_detail":"Padd on kitchen table in house of Sandoval.","color":"whitesmoke","ringAttr":"0","dotAttr":"0","ref_num":"124","ep_num":"25","ep_title":"This Side of Paradise","s":"1","e":"24"},{"whichDotOnSpoke":"0","trope":"Data Pad","tags":"padd","trope_detail":"Red-Skirt with Padd on bridge.","color":"red-Skirt","ringAttr":"0","dotAttr":"0","ref_num":"125","ep_num":"26","ep_title":"The Devil in the Dark","s":"1","e":"25"},{"whichDotOnSpoke":"0","trope":"Data Pad","tags":"padd kirk","trope_detail":"Kirk reads starfleet report on Padd and hands to Red-Skirt.","color":"kirk","ringAttr":"1","dotAttr":"0","ref_num":"126","ep_num":"27","ep_title":"Errand of Mercy","s":"1","e":"26"},{"whichDotOnSpoke":"1","trope":"Data Pad","tags":"padd spock","trope_detail":"Spock writes on Padd.","color":"spock","ringAttr":"1","dotAttr":"0","ref_num":"126","ep_num":"27","ep_title":"Errand of Mercy","s":"1","e":"26"},{"whichDotOnSpoke":"0","trope":"Data Pad","tags":"padd","trope_detail":"Lt. Charlene Masters with Padd on bridge.","color":"blue-Skirt","ringAttr":"0","dotAttr":"0","ref_num":"127","ep_num":"28","ep_title":"The Alternative Factor","s":"1","e":"27"},{"whichDotOnSpoke":"1","trope":"Data Pad","tags":"padd","trope_detail":"Lt. Charlene Masters with Padd on table.","color":"blue-Skirt","ringAttr":"0","dotAttr":"0","ref_num":"127","ep_num":"28","ep_title":"The Alternative Factor","s":"1","e":"27"},{"whichDotOnSpoke":"2","trope":"Data Pad","tags":"padd","trope_detail":"Lt. Charlene Masters with Padd to engineering and hands to Redshirt.","color":"blue-Skirt","ringAttr":"0","dotAttr":"0","ref_num":"127","ep_num":"28","ep_title":"The Alternative Factor","s":"1","e":"27"},{"whichDotOnSpoke":"3","trope":"Data Pad","tags":"padd small","trope_detail":"Lt. Charlene Masters with Padd (small).","color":"charlene_masters","ringAttr":"0","dotAttr":"0","ref_num":"127","ep_num":"28","ep_title":"The Alternative Factor","s":"1","e":"27"},{"whichDotOnSpoke":"4","trope":"Data Pad","tags":"padd","trope_detail":"Gold-Skirt hands Padd to Kirk to sign.","color":"gold-Skirt","ringAttr":"0","dotAttr":"0","ref_num":"127","ep_num":"28","ep_title":"The Alternative Factor","s":"1","e":"27"},{"whichDotOnSpoke":"5","trope":"Data Pad","tags":"padd small","trope_detail":"Yeoman Zahra with Padd on bridge.","color":"red-Skirt","ringAttr":"0","dotAttr":"0","ref_num":"127","ep_num":"28","ep_title":"The Alternative Factor","s":"1","e":"27"},{"whichDotOnSpoke":"6","trope":"Data Pad","tags":"padd uhura","trope_detail":"Uhura with Padd on bridge.","color":"uhura","ringAttr":"1","dotAttr":"0","ref_num":"127","ep_num":"28","ep_title":"The Alternative Factor","s":"1","e":"27"},{"whichDotOnSpoke":"7","trope":"Data Pad","tags":"padd uhura","trope_detail":"Uhura with Padd on bridge.","color":"uhura","ringAttr":"1","dotAttr":"0","ref_num":"127","ep_num":"28","ep_title":"The Alternative Factor","s":"1","e":"27"},{"whichDotOnSpoke":"8","trope":"Data Pad","tags":"padd uhura","trope_detail":"Uhura writes on Padd on bridge.","color":"uhura","ringAttr":"1","dotAttr":"0","ref_num":"127","ep_num":"28","ep_title":"The Alternative Factor","s":"1","e":"27"},{"whichDotOnSpoke":"0","trope":"Data Pad","tags":"padd small uhura","trope_detail":"Uhura records landing party on Padd.","color":"uhura","ringAttr":"1","dotAttr":"0","ref_num":"128","ep_num":"29","ep_title":"The City on the Edge of Forever","s":"1","e":"28"},{"whichDotOnSpoke":"1","trope":"Data Pad","tags":"padd uhura","trope_detail":"Uhura write orders from Kirk on Padd.","color":"uhura","ringAttr":"1","dotAttr":"0","ref_num":"128","ep_num":"29","ep_title":"The City on the Edge of Forever","s":"1","e":"28"},{"whichDotOnSpoke":"2","trope":"Data Pad","tags":"padd uhura","trope_detail":"Uhura writes on Padd.","color":"uhura","ringAttr":"1","dotAttr":"0","ref_num":"128","ep_num":"29","ep_title":"The City on the Edge of Forever","s":"1","e":"28"},{"whichDotOnSpoke":"0","trope":"Data Pad","tags":"padd","trope_detail":"McCoy writes on Padd.","color":"mccoy","ringAttr":"0","dotAttr":"2","ref_num":"129","ep_num":"30","ep_title":"Operation: Annihilate!","s":"1","e":"29"},{"whichDotOnSpoke":"1","trope":"Data Pad","tags":"padd","trope_detail":"Padd on desk in sick bay.","color":"mccoy","ringAttr":"0","dotAttr":"2","ref_num":"129","ep_num":"30","ep_title":"Operation: Annihilate!","s":"1","e":"29"},{"whichDotOnSpoke":"2","trope":"Data Pad","tags":"padd","trope_detail":"Nurse Chapel with Padd in sick bay.","color":"nurse_chapel","ringAttr":"0","dotAttr":"1","ref_num":"129","ep_num":"30","ep_title":"Operation: Annihilate!","s":"1","e":"29"},{"whichDotOnSpoke":"3","trope":"Data Pad","tags":"padd","trope_detail":"Nurse Chapel writes on Padd.","color":"nurse_chapel","ringAttr":"0","dotAttr":"1","ref_num":"129","ep_num":"30","ep_title":"Operation: Annihilate!","s":"1","e":"29"},{"whichDotOnSpoke":"4","trope":"Data Pad","tags":"padd small","trope_detail":"Nurse Chapel writes on Padd.","color":"nurse_chapel","ringAttr":"0","dotAttr":"1","ref_num":"129","ep_num":"30","ep_title":"Operation: Annihilate!","s":"1","e":"29"},{"whichDotOnSpoke":"5","trope":"Data Pad","tags":"padd","trope_detail":"Yeoman Kahra with Padd on bridge.","color":"red-Skirt","ringAttr":"0","dotAttr":"0","ref_num":"129","ep_num":"30","ep_title":"Operation: Annihilate!","s":"1","e":"29"},{"whichDotOnSpoke":"6","trope":"Data Pad","tags":"padd","trope_detail":"Yeoman Zahra with Padd on bridge.","color":"red-Skirt","ringAttr":"0","dotAttr":"0","ref_num":"129","ep_num":"30","ep_title":"Operation: Annihilate!","s":"1","e":"29"},{"whichDotOnSpoke":"7","trope":"Data Pad","tags":"padd small scotty","trope_detail":"Scotty with Padd in transport room.","color":"scotty","ringAttr":"0","dotAttr":"2","ref_num":"129","ep_num":"30","ep_title":"Operation: Annihilate!","s":"1","e":"29"},{"whichDotOnSpoke":"8","trope":"Data Pad","tags":"padd spock","trope_detail":"Spock with Padd on bridge.","color":"spock","ringAttr":"1","dotAttr":"0","ref_num":"129","ep_num":"30","ep_title":"Operation: Annihilate!","s":"1","e":"29"},{"whichDotOnSpoke":"9","trope":"Data Pad","tags":"padd spock","trope_detail":"Spock writes on Padd and hands to technician.","color":"spock","ringAttr":"1","dotAttr":"0","ref_num":"129","ep_num":"30","ep_title":"Operation: Annihilate!","s":"1","e":"29"},{"whichDotOnSpoke":"10","trope":"Data Pad","tags":"padd uhura","trope_detail":"Uhura with Padd on bridge.","color":"uhura","ringAttr":"1","dotAttr":"0","ref_num":"129","ep_num":"30","ep_title":"Operation: Annihilate!","s":"1","e":"29"},{"whichDotOnSpoke":"0","trope":"Data Pad","tags":"padd","trope_detail":"Blue-Skirt with Padd in corridor.","color":"blue-Skirt","ringAttr":"0","dotAttr":"0","ref_num":"201","ep_num":"31","ep_title":"Amok Time","s":"2","e":"1"},{"whichDotOnSpoke":"1","trope":"Data Pad","tags":"padd","trope_detail":"Gold-Skirt with Padd on bridge.","color":"gold-Skirt","ringAttr":"0","dotAttr":"0","ref_num":"201","ep_num":"31","ep_title":"Amok Time","s":"2","e":"1"},{"whichDotOnSpoke":"2","trope":"Data Pad","tags":"padd small","trope_detail":"Gold-Skirt with Padd on bridge.","color":"gold-Skirt","ringAttr":"0","dotAttr":"0","ref_num":"201","ep_num":"31","ep_title":"Amok Time","s":"2","e":"1"},{"whichDotOnSpoke":"3","trope":"Data Pad","tags":"padd kirk","trope_detail":"Kirk signs Padd","color":"kirk","ringAttr":"1","dotAttr":"0","ref_num":"201","ep_num":"31","ep_title":"Amok Time","s":"2","e":"1"},{"whichDotOnSpoke":"4","trope":"Data Pad","tags":"padd","trope_detail":"McCoy with Padd on desk in sick bay.","color":"mccoy","ringAttr":"0","dotAttr":"2","ref_num":"201","ep_num":"31","ep_title":"Amok Time","s":"2","e":"1"},{"whichDotOnSpoke":"5","trope":"Data Pad","tags":"padd","trope_detail":"McCoy writes on Padd in sick bay.","color":"mccoy","ringAttr":"0","dotAttr":"2","ref_num":"201","ep_num":"31","ep_title":"Amok Time","s":"2","e":"1"},{"whichDotOnSpoke":"6","trope":"Data Pad","tags":"padd small","trope_detail":"Nurse Chapel hands Padd to McCoy.","color":"nurse_chapel","ringAttr":"0","dotAttr":"1","ref_num":"201","ep_num":"31","ep_title":"Amok Time","s":"2","e":"1"},{"whichDotOnSpoke":"7","trope":"Data Pad","tags":"padd","trope_detail":"Nurse Chapel writes on Padd at desk in sick bay.","color":"nurse_chapel","ringAttr":"0","dotAttr":"1","ref_num":"201","ep_num":"31","ep_title":"Amok Time","s":"2","e":"1"},{"whichDotOnSpoke":"8","trope":"Data Pad","tags":"padd small","trope_detail":"Redshirt with Padd in corridor.","color":"redshirt","ringAttr":"0","dotAttr":"0","ref_num":"201","ep_num":"31","ep_title":"Amok Time","s":"2","e":"1"},{"whichDotOnSpoke":"9","trope":"Data Pad","tags":"padd spock","trope_detail":"Padd on desk in Spocks quarters.","color":"spock","ringAttr":"1","dotAttr":"0","ref_num":"201","ep_num":"31","ep_title":"Amok Time","s":"2","e":"1"},{"whichDotOnSpoke":"10","trope":"Data Pad","tags":"padd spock","trope_detail":"Padd on desk in Spocks quarters.","color":"spock","ringAttr":"1","dotAttr":"0","ref_num":"201","ep_num":"31","ep_title":"Amok Time","s":"2","e":"1"},{"whichDotOnSpoke":"11","trope":"Data Pad","tags":"padd spock","trope_detail":"Spock with Padd sitting on Spocks desk.","color":"spock","ringAttr":"1","dotAttr":"0","ref_num":"201","ep_num":"31","ep_title":"Amok Time","s":"2","e":"1"},{"whichDotOnSpoke":"12","trope":"Data Pad","tags":"padd uhura","trope_detail":"Uhura with Padd on bridge station.","color":"uhura","ringAttr":"1","dotAttr":"0","ref_num":"201","ep_num":"31","ep_title":"Amok Time","s":"2","e":"1"},{"whichDotOnSpoke":"0","trope":"Data Pad","tags":"padd","trope_detail":"Blue-Skirt works on Padd on bridge.","color":"blue-Skirt","ringAttr":"0","dotAttr":"0","ref_num":"202","ep_num":"32","ep_title":"Who Mourns for Adonais?","s":"2","e":"2"},{"whichDotOnSpoke":"1","trope":"Data Pad","tags":"padd small","trope_detail":"Lt. Carolyn Palamas hands Kirk Padd, Kirk reads and hands back.","color":"carolyn_palamas","ringAttr":"0","dotAttr":"0","ref_num":"202","ep_num":"32","ep_title":"Who Mourns for Adonais?","s":"2","e":"2"},{"whichDotOnSpoke":"2","trope":"Data Pad","tags":"padd small kirk","trope_detail":"Padd on arm of captains chair, writes on it.","color":"kirk","ringAttr":"1","dotAttr":"0","ref_num":"202","ep_num":"32","ep_title":"Who Mourns for Adonais?","s":"2","e":"2"},{"whichDotOnSpoke":"3","trope":"Data Pad","tags":"padd small spock","trope_detail":"Spock writes on Padd on bridge after Apollos giant hand grabs ship, hands to Mr. Kyle.","color":"spock","ringAttr":"1","dotAttr":"0","ref_num":"202","ep_num":"32","ep_title":"Who Mourns for Adonais?","s":"2","e":"2"},{"whichDotOnSpoke":"4","trope":"Data Pad","tags":"padd small spock","trope_detail":"Spock writes on Padd on bridge after Apollos giant hand grabs ship.","color":"spock","ringAttr":"1","dotAttr":"0","ref_num":"202","ep_num":"32","ep_title":"Who Mourns for Adonais?","s":"2","e":"2"},{"whichDotOnSpoke":"5","trope":"Data Pad","tags":"padd small uhura","trope_detail":"Uhura with Padd on bridge.","color":"uhura","ringAttr":"1","dotAttr":"0","ref_num":"202","ep_num":"32","ep_title":"Who Mourns for Adonais?","s":"2","e":"2"},{"whichDotOnSpoke":"6","trope":"Data Pad","tags":"padd uhura","trope_detail":"Uhura with Padd on bridge.","color":"uhura","ringAttr":"1","dotAttr":"0","ref_num":"202","ep_num":"32","ep_title":"Who Mourns for Adonais?","s":"2","e":"2"},{"whichDotOnSpoke":"0","trope":"Data Pad","tags":"padd","trope_detail":"Gold-Skirt with Padd on bridge.","color":"gold-Skirt","ringAttr":"0","dotAttr":"0","ref_num":"203","ep_num":"33","ep_title":"The Changeling","s":"2","e":"3"},{"whichDotOnSpoke":"1","trope":"Data Pad","tags":"padd","trope_detail":"Lt. Singh with Padd in auxillary control.","color":"redshirt","ringAttr":"0","dotAttr":"0","ref_num":"203","ep_num":"33","ep_title":"The Changeling","s":"2","e":"3"},{"whichDotOnSpoke":"2","trope":"Data Pad","tags":"padd","trope_detail":"Redshirt technician with Padd in transporter room.","color":"redshirt","ringAttr":"0","dotAttr":"0","ref_num":"203","ep_num":"33","ep_title":"The Changeling","s":"2","e":"3"},{"whichDotOnSpoke":"3","trope":"Data Pad","tags":"padd spock","trope_detail":"Spock holds padd at bridge station, reads report to Kirk.","color":"spock","ringAttr":"1","dotAttr":"0","ref_num":"203","ep_num":"33","ep_title":"The Changeling","s":"2","e":"3"},{"whichDotOnSpoke":"4","trope":"Data Pad","tags":"padd small uhura","trope_detail":"Uhura trades Padd for Padd (small), writes on Padd (small).","color":"uhura","ringAttr":"1","dotAttr":"0","ref_num":"203","ep_num":"33","ep_title":"The Changeling","s":"2","e":"3"},{"whichDotOnSpoke":"5","trope":"Data Pad","tags":"padd uhura","trope_detail":"Uhura with Padd at bridge station, writes on Padd.","color":"uhura","ringAttr":"1","dotAttr":"0","ref_num":"203","ep_num":"33","ep_title":"The Changeling","s":"2","e":"3"},{"whichDotOnSpoke":"6","trope":"Data Pad","tags":"padd","trope_detail":"Padd sits on engineering console.","color":"whitesmoke","ringAttr":"0","dotAttr":"0","ref_num":"203","ep_num":"33","ep_title":"The Changeling","s":"2","e":"3"},{"whichDotOnSpoke":"0","trope":"Data Pad","tags":"padd","trope_detail":"Lt. Marlena Moreau hands Kirk the Padd to sign. Kirk stares at her for a minute, signs it, and hands back. McCoy asks if he knows her.","color":"red-Skirt","ringAttr":"0","dotAttr":"0","ref_num":"204","ep_num":"34","ep_title":"Mirror, Mirror","s":"2","e":"4"},{"whichDotOnSpoke":"1","trope":"Data Pad","tags":"padd uhura","trope_detail":"Uhura hands Kirk a Padd.","color":"uhura","ringAttr":"1","dotAttr":"0","ref_num":"204","ep_num":"34","ep_title":"Mirror, Mirror","s":"2","e":"4"},{"whichDotOnSpoke":"0","trope":"Data Pad","tags":"padd","trope_detail":"Kyle writes on Padd, hands to Scotty.","color":"goldshirt","ringAttr":"0","dotAttr":"0","ref_num":"205","ep_num":"35","ep_title":"The Apple","s":"2","e":"5"},{"whichDotOnSpoke":"1","trope":"Data Pad","tags":"padd scotty","trope_detail":"Red-Skirt hands Scotty a Padd.","color":"scotty","ringAttr":"0","dotAttr":"2","ref_num":"205","ep_num":"35","ep_title":"The Apple","s":"2","e":"5"},{"whichDotOnSpoke":"2","trope":"Data Pad","tags":"padd","trope_detail":"Technician has Padd on bridge.","color":"whitesmoke","ringAttr":"0","dotAttr":"0","ref_num":"205","ep_num":"35","ep_title":"The Apple","s":"2","e":"5"},{"whichDotOnSpoke":"0","trope":"Data Pad","tags":"padd, small","trope_detail":"Blueshirt with tricoder near shuttlebay","color":"blueshirt","ringAttr":"0","dotAttr":"0","ref_num":"206","ep_num":"36","ep_title":"The Doomsday Machine","s":"2","e":"6"},{"whichDotOnSpoke":"1","trope":"Data Pad","tags":"padd","trope_detail":"Blue-Skirt with padd on the bridge","color":"blue-Skirt","ringAttr":"0","dotAttr":"0","ref_num":"206","ep_num":"36","ep_title":"The Doomsday Machine","s":"2","e":"6"},{"whichDotOnSpoke":"2","trope":"Data Pad","tags":"padd","trope_detail":"Gold-Skirt with padd on the bridge","color":"gold-Skirt","ringAttr":"0","dotAttr":"0","ref_num":"206","ep_num":"36","ep_title":"The Doomsday Machine","s":"2","e":"6"},{"whichDotOnSpoke":"3","trope":"Data Pad","tags":"padd, small","trope_detail":"Lt. Palmer and two technicans working on Communication station","color":"red-Skirt","ringAttr":"0","dotAttr":"0","ref_num":"206","ep_num":"36","ep_title":"The Doomsday Machine","s":"2","e":"6"},{"whichDotOnSpoke":"4","trope":"Data Pad","tags":"padd","trope_detail":"Red-Skirt at communication station with padd","color":"red-Skirt","ringAttr":"0","dotAttr":"0","ref_num":"206","ep_num":"36","ep_title":"The Doomsday Machine","s":"2","e":"6"},{"whichDotOnSpoke":"5","trope":"Data Pad","tags":"padd spock","trope_detail":"Spock receives padd from Sulu calculating path of Doomsday Machine.","color":"spock","ringAttr":"1","dotAttr":"0","ref_num":"206","ep_num":"36","ep_title":"The Doomsday Machine","s":"2","e":"6"},{"whichDotOnSpoke":"6","trope":"Data Pad","tags":"padd spock","trope_detail":"Spock writes on padd and hands to Blue-Skirt.","color":"spock","ringAttr":"1","dotAttr":"0","ref_num":"206","ep_num":"36","ep_title":"The Doomsday Machine","s":"2","e":"6"},{"whichDotOnSpoke":"0","trope":"Data Pad","tags":"padd","trope_detail":"Red-Skirt with Padd on bridge.","color":"red-Skirt","ringAttr":"0","dotAttr":"0","ref_num":"207","ep_num":"37","ep_title":"Catspaw","s":"2","e":"7"},{"whichDotOnSpoke":"0","trope":"Data Pad","tags":"padd uhura","trope_detail":"Uhura with padd on bridge","color":"uhura","ringAttr":"1","dotAttr":"0","ref_num":"208","ep_num":"38","ep_title":"I, Mudd","s":"2","e":"8"},{"whichDotOnSpoke":"0","trope":"Data Pad","tags":"padd uhura","trope_detail":"Uhura with padd at communication station","color":"uhura","ringAttr":"1","dotAttr":"0","ref_num":"209","ep_num":"39","ep_title":"Metamorphosis","s":"2","e":"9"}]