[{"":"","trope":"Forcful Kiss","tags":"love kiss","trope_detail":"Kirk forces Andrea to kiss him to break her programming.","color":"gold","ringAttr":"1","dotAttr":"","ref_num":"107","ep_num":"8","ep_title":"What Are Little Girls Made Of?","s":"1","e":"7","whichDotOnSpoke":"0"},{"":"","trope":"Kissing Under The Influence","tags":"love kiss","trope_detail":"Dr. Corby commands Andrea to kiss himself.","color":"white","ringAttr":"","dotAttr":"","ref_num":"107","ep_num":"8","ep_title":"What Are Little Girls Made Of?","s":"1","e":"7","whichDotOnSpoke":"1"},{"":"","trope":"Kissing Under The Influence","tags":"love kiss","trope_detail":"Dr. Corby commands Andrea to kiss Kirk.","color":"white","ringAttr":"","dotAttr":"","ref_num":"107","ep_num":"8","ep_title":"What Are Little Girls Made Of?","s":"1","e":"7","whichDotOnSpoke":"2"},{"":"","trope":"Reunion Kiss","tags":"love kiss","trope_detail":"Nurse Chapel and Dr. Corby kiss after being separated for many years ago.","color":"cornflowerblue","ringAttr":"","dotAttr":"1","ref_num":"107","ep_num":"8","ep_title":"What Are Little Girls Made Of?","s":"1","e":"7","whichDotOnSpoke":"3"},{"":"","trope":"Big Damn Kiss","tags":"love kiss","trope_detail":"Kirk, after neural suggestion, plants a big, wet kiss on Dr. Helen Noel.","color":"gold","ringAttr":"1","dotAttr":"","ref_num":"109","ep_num":"10","ep_title":"Dagger of the Mind","s":"1","e":"9","whichDotOnSpoke":"0"},{"":"","trope":"Almost Kiss","tags":"love kiss","trope_detail":"Averted: Kirk and Lenore ready to kiss but find a dead body.","color":"white","ringAttr":"","dotAttr":"","ref_num":"113","ep_num":"14","ep_title":"The Conscience of the King","s":"1","e":"13","whichDotOnSpoke":"0"},{"":"","trope":"Hollywood Kiss","tags":"love kiss","trope_detail":"Kirk and Ruth have a kiss of remembrance of good times.","color":"gold","ringAttr":"1","dotAttr":"","ref_num":"115","ep_num":"16","ep_title":"Shore Leave","s":"1","e":"15","whichDotOnSpoke":"0"},{"":"","trope":"Kiss Of Death***","tags":"love kiss","trope_detail":"Kirk and Areel Shaw kiss . Then she tells him she's the prosecuter.","color":"gold","ringAttr":"1","dotAttr":"","ref_num":"120","ep_num":"21","ep_title":"Court Martial","s":"1","e":"20","whichDotOnSpoke":"0"},{"":"","trope":"All Girls Want Bad Boys","tags":"love kiss","trope_detail":"Khan kisses Lt. McGivers. She hesitates then kisses him back.","color":"white","ringAttr":"","dotAttr":"","ref_num":"122","ep_num":"23","ep_title":"Space Seed","s":"1","e":"22","whichDotOnSpoke":"0"},{"":"","trope":"True Love's Kiss","tags":"love kiss","trope_detail":"Spock kisses Lella.","color":"cornflowerblue","ringAttr":"1","dotAttr":"","ref_num":"124","ep_num":"25","ep_title":"This Side of Paradise","s":"1","e":"24","whichDotOnSpoke":"0"},{"":"","trope":"True Love's Kiss","tags":"love kiss","trope_detail":"Spock kisses Lella.","color":"cornflowerblue","ringAttr":"1","dotAttr":"","ref_num":"124","ep_num":"25","ep_title":"This Side of Paradise","s":"1","e":"24","whichDotOnSpoke":"1"},{"":"","trope":"True Love's Kiss","tags":"love kiss","trope_detail":"Spock kisses Lella.","color":"cornflowerblue","ringAttr":"1","dotAttr":"","ref_num":"124","ep_num":"25","ep_title":"This Side of Paradise","s":"1","e":"24","whichDotOnSpoke":"2"},{"":"","trope":"True Love's Kiss","tags":"love kiss","trope_detail":"Edith Keeler kisses Kirk in a passionate manner.","color":"white","ringAttr":"","dotAttr":"","ref_num":"128","ep_num":"29","ep_title":"The City on the Edge of Forever","s":"1","e":"28","whichDotOnSpoke":"0"},{"":"","trope":"True Love's Kiss","tags":"love kiss","trope_detail":"Apollo lays a big kiss on Lt. Carolyn Palamas, again.","color":"white","ringAttr":"","dotAttr":"","ref_num":"202","ep_num":"32","ep_title":"Who Mourns for Adonais?","s":"2","e":"2","whichDotOnSpoke":"0"},{"":"","trope":"True Love's Kiss","tags":"love kiss","trope_detail":"Lt. Carolyn Palamas kisses Apollo in loving fashion.","color":"cornflowerblue","ringAttr":"","dotAttr":"","ref_num":"202","ep_num":"32","ep_title":"Who Mourns for Adonais?","s":"2","e":"2","whichDotOnSpoke":"1"},{"":"","trope":"Big Damn Kiss","tags":"love kiss","trope_detail":"Kirk kisses Mirror Lt. Marlena Moreau.","color":"gold","ringAttr":"1","dotAttr":"","ref_num":"204","ep_num":"34","ep_title":"Mirror, Mirror","s":"2","e":"4","whichDotOnSpoke":"0"},{"":"","trope":"kiss***","tags":"love kiss","trope_detail":"Mirror Lt. Marlena Mareau kisses Kirk while she's coming on and being sexy.","color":"red","ringAttr":"","dotAttr":"","ref_num":"204","ep_num":"34","ep_title":"Mirror, Mirror","s":"2","e":"4","whichDotOnSpoke":"1"},{"":"","trope":"Almost Kiss","tags":"love kiss","trope_detail":"Averted: Kirk returns.","color":"white","ringAttr":"","dotAttr":"","ref_num":"205","ep_num":"35","ep_title":"The Apple","s":"2","e":"5","whichDotOnSpoke":"0"},{"":"","trope":"kiss***","tags":"love kiss","trope_detail":"Chekov kisses Yeoman Martha Landon.","color":"gold","ringAttr":"","dotAttr":"2","ref_num":"205","ep_num":"35","ep_title":"The Apple","s":"2","e":"5","whichDotOnSpoke":"1"},{"":"","trope":"kiss***","tags":"love kiss","trope_detail":"Chekov kisses Yeoman Martha Landon's neck.","color":"gold","ringAttr":"","dotAttr":"2","ref_num":"205","ep_num":"35","ep_title":"The Apple","s":"2","e":"5","whichDotOnSpoke":"2"},{"":"","trope":"kiss***","tags":"love kiss","trope_detail":"Kirk kisses Sylvia passionately and she kisses him back.","color":"gold","ringAttr":"1","dotAttr":"","ref_num":"207","ep_num":"37","ep_title":"Catspaw","s":"2","e":"7","whichDotOnSpoke":"0"},{"":"","trope":"kiss***","tags":"love kiss","trope_detail":"Kirk kisses Sylvia. | Kirk: 'You're a very beautiful woman.'","color":"gold","ringAttr":"1","dotAttr":"","ref_num":"207","ep_num":"37","ep_title":"Catspaw","s":"2","e":"7","whichDotOnSpoke":"1"},{"":"","trope":"kissing under the influence","tags":"love kiss","trope_detail":"Forced to kiss by telekenetic aliens.","color":"white","ringAttr":"","dotAttr":"","ref_num":"310","ep_num":"66","ep_title":"Plato's Stepchildren","s":"3","e":"10","whichDotOnSpoke":"0"},{"":"","trope":"kissing under the influence","tags":"love kiss","trope_detail":"Forced to kiss by telekenetic aliens.","color":"white","ringAttr":"","dotAttr":"","ref_num":"310","ep_num":"66","ep_title":"Plato's Stepchildren","s":"3","e":"10","whichDotOnSpoke":"1"}]